{
  "stock": "AARTIIND",
  "ltp": "524.25",
  "open": "524.25",
  "price": "508.85",
  "high": "526.75",
  "low": "508.4",
  "td_hl_cross": "-",
  "change_rs": "-15.4",
  "change_percentage": "-2.94",
  "volume": "856.7K",
  "avrg_volume": "1,522.4K",
  "volume_spike": "▼43.7%",
  "open_hl": "-",
  "pre_day_high": "Error",
  "pre_day_low": "Error",
  "pre_hl_cross": "Pre_DLow_Break",
  "month_high": "592.8",
  "month_low": "509.05",
  "month_hl_cross": "30D_Low_Break",
  "year_high": "769.25",
  "year_low": "438",
  "year_hl_cross": "-"
}